LICENCE.txt
MANIFEST.in
README.md
requirements-build.txt
requirements-docs.txt
requirements-test.txt
requirements.txt
setup.cfg
setup.py
src/smk/__init__.py
src/smk/cli.py
src/smk.egg-info/PKG-INFO
src/smk.egg-info/SOURCES.txt
src/smk.egg-info/dependency_links.txt
src/smk.egg-info/entry_points.txt
src/smk.egg-info/not-zip-safe
src/smk.egg-info/requires.txt
src/smk.egg-info/top_level.txt